{
  "/2015/08/30/obwat.html": "<i>O Brother, Where Art Thou?</i>",
  "/2015/09/08/wesAnd.html": "Wes Anderson's Wes Anderson",
  "/2015/11/03/harakiri.html": "Review: <i>Harakiri</i>",
  "/2015/10/30/crimsonpeak.html": "Review: <i>Crimson Peak</i>",
  "/2015/08/30/drive.html": "Duality in <i>Drive</i>",
  "/2015/10/22/hardeight.html": "Hard Eight: The Weekly Beat 10/22",
  "/2015/09/22/enemy.html": "The Chaotic Order of <i>Enemy</i>",
  "/2015/11/24/MockingjayReview.html": "Review: <i>The Hunger Games: Mockingjay - Part 2</i>",
  "/2015/11/05/hardeight.html": "Hard Eight: The Weekly Beat 11/05",
  "/2015/08/30/ogf.html": "<i>Only God Forgives</i>",
  "/2015/09/15/scorVoy.html": "Scorsese's Voyage",
  "/2015/11/27/InsideOutRev.html": "Review: <i>Inside Out</i>",
  "/2015/11/19/hardeight.html": "Hard Eight: The Weekly Beat 11/19",
  "/2015/10/13/EverestReview.html": "Review: <i>Everest</i>",
  "/2015/12/04/Youth.html": "Ceiling Gazing: <i>Youth</i>",
  "/2015/08/31/endoftour.html": "First Impressions: <i>The End of the Tour</i>",
  "/2015/10/27/junun.html": "Review: <i>Junun</i>",
  "/2015/11/02/podcast2.html": "Podcast 2: Beasts of No Nation",
  "/2015/10/16/elorfanato.html": "Weekly Horror: <i>El Orfanato</i>",
  "/2015/10/29/hardeight.html": "Hard Eight: The Weekly Beat 10/29",
  "/2015/10/11/evildead.html": "Weekly Horror: <i>The Evil Dead</i>",
  "/2015/12/04/hardeight.html": "Hard Eight: The Weekly Beat 12/03",
  "/2015/11/24/padayappa.html": "<i>Padayappa:</i> The Quintessential Tamil Family Film",
  "/2015/11/25/tokyochorus.html": "Ozu's <i>Tokyo Chorus</i>",
  "/2015/08/30/FFP2015.html": "The Moviegoer's Fall Film Preview",
  "/2015/10/20/yojimbo.html": "PCI Preview: <i>Yojimbo</i> ",
  "/2015/11/14/lobster.html": "PFF Review: <i>The Lobster</i>",
  "/2015/12/15/podcast8.html": "Podcast: <i>Krampus</i>",
  "/2015/11/18/podcast5.html": "Podcast: <i>Spotlight</i>",
  "/2015/11/26/NightBeforeRev.html": "Review: <i>The Night Before</i>",
  "/2015/09/30/listenup.html": "Review: <i>Listen Up Philip</i>",
  "/2015/12/01/HolyMotors.html": "The Profound Weirdness of <i>Holy Motors</i>",
  "/2015/10/01/martRev.html": "Review: <i>The Martian</i>",
  "/2015/10/09/PFFprev.html": "Philadelphia Film Festival Preview",
  "/2015/10/24/podcast1.html": "Podcast 1: Steve Jobs",
  "/2015/10/17/hardeight.html": "Hard Eight: The Weekly Beat 10/16",
  "/2015/11/30/ikilledmymother.html": "The Work of Xavier Dolan: <i>I Killed My Mother</i>",
  "/2015/09/04/bmprev.html": "Preview: <i>Black Mass</i>",
  "/2015/11/12/hardeight.html": "Hard Eight: The Weekly Beat 11/12",
  "/2015/11/10/SpectreRev.html": "Review: <i>Spectre</i>",
  "/2015/09/10/ootFurnace.html": "<i>Out Of The Furnace</i>’s Lost Dirge to the American Dream",
  "/2015/12/09/thebirds.html": "<i>The Birds</i>",
  "/2015/11/11/podcast4.html": "Podcast: <i>Spectre</i>",
  "/2015/11/01/atb.html": "Around the Block 11/01",
  "/2015/10/18/atb.html": "Around the Block 10/18",
  "/2015/12/11/hardeight.html": "Hard Eight: The Weekly Beat 12/10",
  "/2015/11/08/atb.html": "Around the Block 11/08",
  "/2015/12/08/heartbeats.html": "The Work of Xavier Dolan: <i>Heartbeats</i>",
  "/2015/10/05/boyhood.html": "Revisiting <i>Boyhood</i>",
  "/2015/11/05/podcast3.html": "Podcast 3: Victoria",
  "/2015/10/30/hausu.html": "Weekly Horror: <i>Hausu</i>",
  "/2015/11/22/dheepan.html": "PFF Review: <i>Dheepan</i>",
  "/2015/12/07/podcast7.html": "Podcast: <i>Creed</i>",
  "/2015/10/24/ltroi.html": "Weekly Horror: <i>Let the Right One In</i>",
  "/2015/10/19/HerReview.html": "Review: <i>Her</i>",
  "/2015/10/26/deltoro.html": "<i>Monsters of Our Own</i>: A Guillermo Del Toro Retrospective",
  "/2015/11/15/atb.html": "Around the Block 11/15",
  "/2015/11/25/podcast6.html": "Podcast: <i>Brooklyn</i>",
  "/2015/08/30/persona.html": "<i>Persona</i>",
  "/2015/11/22/highsun.html": "PFF Review: <i>The High Sun (Zvizdan)</i>",
  "/2015/12/03/windrises.html": "<i>The Wind Rises</i>... We Must Try to Live",
  "/2015/09/21/RBrecap.html": "Recap: <i>Raging Bull</i>",
  "/2015/10/24/atb.html": "Around the Block 10/25",
  "/2015/12/04/macbethrev.html": "Review: <i>Macbeth</i>",
  "/2015/10/28/mulhollanddrive.html": "Lynch's Surreal Haze: <i>Mulholland Drive</i>",
  "/2015/11/09/decameron.html": "Pasolini's Sin: <i>The Decameron</i>",
  "/2015/11/25/hardeight.html": "Hard Eight: The Weekly Beat 11/25",
  "/2015/09/24/BlackMass.html": "Southies: The City and The Family in <i>Black Mass</i>",
  "/2015/11/04/fiveeasypieces.html": "Review: <i>Five Easy Pieces</i>"
}